<?xml version="1.0" encoding="utf-8"?>
<!DOCTYPE rrd SYSTEM "http://oss.oetiker.ch/rrdtool/rrdtool.dtd">
<!-- Round Robin Database Dump -->
<rrd>
	<version>0003</version>
	<step>60</step> <!-- Seconds -->
	<lastupdate>1582763969</lastupdate> <!-- 2020-02-26 18:39:29 CST -->

	<ds>
		<name> inoctets </name>
		<type> COUNTER </type>
		<minimal_heartbeat>600</minimal_heartbeat>
		<min>NaN</min>
		<max>NaN</max>

		<!-- PDP Status -->
		<last_ds>368</last_ds>
		<value>NaN</value>
		<unknown_sec> 29 </unknown_sec>
	</ds>

	<ds>
		<name> outoctets </name>
		<type> COUNTER </type>
		<minimal_heartbeat>600</minimal_heartbeat>
		<min>NaN</min>
		<max>NaN</max>

		<!-- PDP Status -->
		<last_ds>736</last_ds>
		<value>NaN</value>
		<unknown_sec> 29 </unknown_sec>
	</ds>

	<!-- Round Robin Archives -->
	<rra>
		<cf>AVERAGE</cf>
		<pdp_per_row>1</pdp_per_row> <!-- 60 seconds -->

		<params>
		<xff>5.0000000000e-01</xff>
		</params>
		<cdp_prep>
			<ds>
			<primary_value>0.0000000000e+00</primary_value>
			<secondary_value>0.0000000000e+00</secondary_value>
			<value>NaN</value>
			<unknown_datapoints>0</unknown_datapoints>
			</ds>
			<ds>
			<primary_value>0.0000000000e+00</primary_value>
			<secondary_value>0.0000000000e+00</secondary_value>
			<value>NaN</value>
			<unknown_datapoints>0</unknown_datapoints>
			</ds>
		</cdp_prep>
		<database>
			<!-- 2020-02-26 08:40:00 CST / 1582728000 --> <row><v>NaN</v><v>NaN</v></row>
			<!-- 2020-02-26 08:41:00 CST / 1582728060 --> <row><v>NaN</v><v>NaN</v></row>
			<!-- 2020-02-26 08:42:00 CST / 1582728120 --> <row><v>NaN</v><v>NaN</v></row>
			<!-- 2020-02-26 08:43:00 CST / 1582728180 --> <row><v>NaN</v><v>NaN</v></row>
			<!-- 2020-02-26 08:44:00 CST / 1582728240 --> <row><v>NaN</v><v>NaN</v></row>
			<!-- 2020-02-26 08:45:00 CST / 1582728300 --> <row><v>NaN</v><v>NaN</v></row>
			<!-- 2020-02-26 08:46:00 CST / 1582728360 --> <row><v>NaN</v><v>NaN</v></row>
			<!-- 2020-02-26 08:47:00 CST / 1582728420 --> <row><v>NaN</v><v>NaN</v></row>
			<!-- 2020-02-26 08:48:00 CST / 1582728480 --> <row><v>NaN</v><v>NaN</v></row>
			<!-- 2020-02-26 08:49:00 CST / 1582728540 --> <row><v>NaN</v><v>NaN</v></row>
			<!-- 2020-02-26 08:50:00 CST / 1582728600 --> <row><v>NaN</v><v>NaN</v></row>
			<!-- 2020-02-26 08:51:00 CST / 1582728660 --> <row><v>NaN</v><v>NaN</v></row>
			<!-- 2020-02-26 08:52:00 CST / 1582728720 --> <row><v>NaN</v><v>NaN</v></row>
			<!-- 2020-02-26 08:53:00 CST / 1582728780 --> <row><v>NaN</v><v>NaN</v></row>
			<!-- 2020-02-26 08:54:00 CST / 1582728840 --> <row><v>NaN</v><v>NaN</v></row>
			<!-- 2020-02-26 08:55:00 CST / 1582728900 --> <row><v>NaN</v><v>NaN</v></row>
			<!-- 2020-02-26 08:56:00 CST / 1582728960 --> <row><v>NaN</v><v>NaN</v></row>
			<!-- 2020-02-26 08:57:00 CST / 1582729020 --> <row><v>NaN</v><v>NaN</v></row>
			<!-- 2020-02-26 08:58:00 CST / 1582729080 --> <row><v>NaN</v><v>NaN</v></row>
			<!-- 2020-02-26 08:59:00 CST / 1582729140 --> <row><v>NaN</v><v>NaN</v></row>
			<!-- 2020-02-26 09:00:00 CST / 1582729200 --> <row><v>NaN</v><v>NaN</v></row>
			<!-- 2020-02-26 09:01:00 CST / 1582729260 --> <row><v>NaN</v><v>NaN</v></row>
			<!-- 2020-02-26 09:02:00 CST / 1582729320 --> <row><v>NaN</v><v>NaN</v></row>
			<!-- 2020-02-26 09:03:00 CST / 1582729380 --> <row><v>NaN</v><v>NaN</v></row>
			<!-- 2020-02-26 09:04:00 CST / 1582729440 --> <row><v>NaN</v><v>NaN</v></row>
			<!-- 2020-02-26 09:05:00 CST / 1582729500 --> <row><v>NaN</v><v>NaN</v></row>
			<!-- 2020-02-26 09:06:00 CST / 1582729560 --> <row><v>NaN</v><v>NaN</v></row>
			<!-- 2020-02-26 09:07:00 CST / 1582729620 --> <row><v>NaN</v><v>NaN</v></row>
			<!-- 2020-02-26 09:08:00 CST / 1582729680 --> <row><v>NaN</v><v>NaN</v></row>
			<!-- 2020-02-26 09:09:00 CST / 1582729740 --> <row><v>NaN</v><v>NaN</v></row>
			<!-- 2020-02-26 09:10:00 CST / 1582729800 --> <row><v>NaN</v><v>NaN</v></row>
			<!-- 2020-02-26 09:11:00 CST / 1582729860 --> <row><v>NaN</v><v>NaN</v></row>
			<!-- 2020-02-26 09:12:00 CST / 1582729920 --> <row><v>NaN</v><v>NaN</v></row>
			<!-- 2020-02-26 09:13:00 CST / 1582729980 --> <row><v>NaN</v><v>NaN</v></row>
			<!-- 2020-02-26 09:14:00 CST / 1582730040 --> <row><v>NaN</v><v>NaN</v></row>
			<!-- 2020-02-26 09:15:00 CST / 1582730100 --> <row><v>NaN</v><v>NaN</v></row>
			<!-- 2020-02-26 09:16:00 CST / 1582730160 --> <row><v>NaN</v><v>NaN</v></row>
			<!-- 2020-02-26 09:17:00 CST / 1582730220 --> <row><v>NaN</v><v>NaN</v></row>
			<!-- 2020-02-26 09:18:00 CST / 1582730280 --> <row><v>NaN</v><v>NaN</v></row>
			<!-- 2020-02-26 09:19:00 CST / 1582730340 --> <row><v>NaN</v><v>NaN</v></row>
			<!-- 2020-02-26 09:20:00 CST / 1582730400 --> <row><v>NaN</v><v>NaN</v></row>
			<!-- 2020-02-26 09:21:00 CST / 1582730460 --> <row><v>NaN</v><v>NaN</v></row>
			<!-- 2020-02-26 09:22:00 CST / 1582730520 --> <row><v>NaN</v><v>NaN</v></row>
			<!-- 2020-02-26 09:23:00 CST / 1582730580 --> <row><v>NaN</v><v>NaN</v></row>
			<!-- 2020-02-26 09:24:00 CST / 1582730640 --> <row><v>NaN</v><v>NaN</v></row>
			<!-- 2020-02-26 09:25:00 CST / 1582730700 --> <row><v>NaN</v><v>NaN</v></row>
			<!-- 2020-02-26 09:26:00 CST / 1582730760 --> <row><v>NaN</v><v>NaN</v></row>
			<!-- 2020-02-26 09:27:00 CST / 1582730820 --> <row><v>NaN</v><v>NaN</v></row>
			<!-- 2020-02-26 09:28:00 CST / 1582730880 --> <row><v>NaN</v><v>NaN</v></row>
			<!-- 2020-02-26 09:29:00 CST / 1582730940 --> <row><v>NaN</v><v>NaN</v></row>
			<!-- 2020-02-26 09:30:00 CST / 1582731000 --> <row><v>NaN</v><v>NaN</v></row>
			<!-- 2020-02-26 09:31:00 CST / 1582731060 --> <row><v>NaN</v><v>NaN</v></row>
			<!-- 2020-02-26 09:32:00 CST / 1582731120 --> <row><v>NaN</v><v>NaN</v></row>
			<!-- 2020-02-26 09:33:00 CST / 1582731180 --> <row><v>NaN</v><v>NaN</v></row>
			<!-- 2020-02-26 09:34:00 CST / 1582731240 --> <row><v>NaN</v><v>NaN</v></row>
			<!-- 2020-02-26 09:35:00 CST / 1582731300 --> <row><v>NaN</v><v>NaN</v></row>
			<!-- 2020-02-26 09:36:00 CST / 1582731360 --> <row><v>NaN</v><v>NaN</v></row>
			<!-- 2020-02-26 09:37:00 CST / 1582731420 --> <row><v>NaN</v><v>NaN</v></row>
			<!-- 2020-02-26 09:38:00 CST / 1582731480 --> <row><v>NaN</v><v>NaN</v></row>
			<!-- 2020-02-26 09:39:00 CST / 1582731540 --> <row><v>NaN</v><v>NaN</v></row>
			<!-- 2020-02-26 09:40:00 CST / 1582731600 --> <row><v>NaN</v><v>NaN</v></row>
			<!-- 2020-02-26 09:41:00 CST / 1582731660 --> <row><v>NaN</v><v>NaN</v></row>
			<!-- 2020-02-26 09:42:00 CST / 1582731720 --> <row><v>NaN</v><v>NaN</v></row>
			<!-- 2020-02-26 09:43:00 CST / 1582731780 --> <row><v>NaN</v><v>NaN</v></row>
			<!-- 2020-02-26 09:44:00 CST / 1582731840 --> <row><v>NaN</v><v>NaN</v></row>
			<!-- 2020-02-26 09:45:00 CST / 1582731900 --> <row><v>NaN</v><v>NaN</v></row>
			<!-- 2020-02-26 09:46:00 CST / 1582731960 --> <row><v>NaN</v><v>NaN</v></row>
			<!-- 2020-02-26 09:47:00 CST / 1582732020 --> <row><v>NaN</v><v>NaN</v></row>
			<!-- 2020-02-26 09:48:00 CST / 1582732080 --> <row><v>NaN</v><v>NaN</v></row>
			<!-- 2020-02-26 09:49:00 CST / 1582732140 --> <row><v>NaN</v><v>NaN</v></row>
			<!-- 2020-02-26 09:50:00 CST / 1582732200 --> <row><v>NaN</v><v>NaN</v></row>
			<!-- 2020-02-26 09:51:00 CST / 1582732260 --> <row><v>NaN</v><v>NaN</v></row>
			<!-- 2020-02-26 09:52:00 CST / 1582732320 --> <row><v>NaN</v><v>NaN</v></row>
			<!-- 2020-02-26 09:53:00 CST / 1582732380 --> <row><v>NaN</v><v>NaN</v></row>
			<!-- 2020-02-26 09:54:00 CST / 1582732440 --> <row><v>NaN</v><v>NaN</v></row>
			<!-- 2020-02-26 09:55:00 CST / 1582732500 --> <row><v>NaN</v><v>NaN</v></row>
			<!-- 2020-02-26 09:56:00 CST / 1582732560 --> <row><v>NaN</v><v>NaN</v></row>
			<!-- 2020-02-26 09:57:00 CST / 1582732620 --> <row><v>NaN</v><v>NaN</v></row>
			<!-- 2020-02-26 09:58:00 CST / 1582732680 --> <row><v>NaN</v><v>NaN</v></row>
			<!-- 2020-02-26 09:59:00 CST / 1582732740 --> <row><v>NaN</v><v>NaN</v></row>
			<!-- 2020-02-26 10:00:00 CST / 1582732800 --> <row><v>NaN</v><v>NaN</v></row>
			<!-- 2020-02-26 10:01:00 CST / 1582732860 --> <row><v>NaN</v><v>NaN</v></row>
			<!-- 2020-02-26 10:02:00 CST / 1582732920 --> <row><v>NaN</v><v>NaN</v></row>
			<!-- 2020-02-26 10:03:00 CST / 1582732980 --> <row><v>NaN</v><v>NaN</v></row>
			<!-- 2020-02-26 10:04:00 CST / 1582733040 --> <row><v>NaN</v><v>NaN</v></row>
			<!-- 2020-02-26 10:05:00 CST / 1582733100 --> <row><v>NaN</v><v>NaN</v></row>
			<!-- 2020-02-26 10:06:00 CST / 1582733160 --> <row><v>NaN</v><v>NaN</v></row>
			<!-- 2020-02-26 10:07:00 CST / 1582733220 --> <row><v>NaN</v><v>NaN</v></row>
			<!-- 2020-02-26 10:08:00 CST / 1582733280 --> <row><v>NaN</v><v>NaN</v></row>
			<!-- 2020-02-26 10:09:00 CST / 1582733340 --> <row><v>NaN</v><v>NaN</v></row>
			<!-- 2020-02-26 10:10:00 CST / 1582733400 --> <row><v>NaN</v><v>NaN</v></row>
			<!-- 2020-02-26 10:11:00 CST / 1582733460 --> <row><v>NaN</v><v>NaN</v></row>
			<!-- 2020-02-26 10:12:00 CST / 1582733520 --> <row><v>NaN</v><v>NaN</v></row>
			<!-- 2020-02-26 10:13:00 CST / 1582733580 --> <row><v>NaN</v><v>NaN</v></row>
			<!-- 2020-02-26 10:14:00 CST / 1582733640 --> <row><v>NaN</v><v>NaN</v></row>
			<!-- 2020-02-26 10:15:00 CST / 1582733700 --> <row><v>NaN</v><v>NaN</v></row>
			<!-- 2020-02-26 10:16:00 CST / 1582733760 --> <row><v>NaN</v><v>NaN</v></row>
			<!-- 2020-02-26 10:17:00 CST / 1582733820 --> <row><v>NaN</v><v>NaN</v></row>
			<!-- 2020-02-26 10:18:00 CST / 1582733880 --> <row><v>NaN</v><v>NaN</v></row>
			<!-- 2020-02-26 10:19:00 CST / 1582733940 --> <row><v>NaN</v><v>NaN</v></row>
			<!-- 2020-02-26 10:20:00 CST / 1582734000 --> <row><v>NaN</v><v>NaN</v></row>
			<!-- 2020-02-26 10:21:00 CST / 1582734060 --> <row><v>NaN</v><v>NaN</v></row>
			<!-- 2020-02-26 10:22:00 CST / 1582734120 --> <row><v>NaN</v><v>NaN</v></row>
			<!-- 2020-02-26 10:23:00 CST / 1582734180 --> <row><v>NaN</v><v>NaN</v></row>
			<!-- 2020-02-26 10:24:00 CST / 1582734240 --> <row><v>NaN</v><v>NaN</v></row>
			<!-- 2020-02-26 10:25:00 CST / 1582734300 --> <row><v>NaN</v><v>NaN</v></row>
			<!-- 2020-02-26 10:26:00 CST / 1582734360 --> <row><v>NaN</v><v>NaN</v></row>
			<!-- 2020-02-26 10:27:00 CST / 1582734420 --> <row><v>NaN</v><v>NaN</v></row>
			<!-- 2020-02-26 10:28:00 CST / 1582734480 --> <row><v>NaN</v><v>NaN</v></row>
			<!-- 2020-02-26 10:29:00 CST / 1582734540 --> <row><v>NaN</v><v>NaN</v></row>
			<!-- 2020-02-26 10:30:00 CST / 1582734600 --> <row><v>NaN</v><v>NaN</v></row>
			<!-- 2020-02-26 10:31:00 CST / 1582734660 --> <row><v>NaN</v><v>NaN</v></row>
			<!-- 2020-02-26 10:32:00 CST / 1582734720 --> <row><v>NaN</v><v>NaN</v></row>
			<!-- 2020-02-26 10:33:00 CST / 1582734780 --> <row><v>NaN</v><v>NaN</v></row>
			<!-- 2020-02-26 10:34:00 CST / 1582734840 --> <row><v>NaN</v><v>NaN</v></row>
			<!-- 2020-02-26 10:35:00 CST / 1582734900 --> <row><v>NaN</v><v>NaN</v></row>
			<!-- 2020-02-26 10:36:00 CST / 1582734960 --> <row><v>NaN</v><v>NaN</v></row>
			<!-- 2020-02-26 10:37:00 CST / 1582735020 --> <row><v>NaN</v><v>NaN</v></row>
			<!-- 2020-02-26 10:38:00 CST / 1582735080 --> <row><v>NaN</v><v>NaN</v></row>
			<!-- 2020-02-26 10:39:00 CST / 1582735140 --> <row><v>NaN</v><v>NaN</v></row>
			<!-- 2020-02-26 10:40:00 CST / 1582735200 --> <row><v>NaN</v><v>NaN</v></row>
			<!-- 2020-02-26 10:41:00 CST / 1582735260 --> <row><v>NaN</v><v>NaN</v></row>
			<!-- 2020-02-26 10:42:00 CST / 1582735320 --> <row><v>NaN</v><v>NaN</v></row>
			<!-- 2020-02-26 10:43:00 CST / 1582735380 --> <row><v>NaN</v><v>NaN</v></row>
			<!-- 2020-02-26 10:44:00 CST / 1582735440 --> <row><v>NaN</v><v>NaN</v></row>
			<!-- 2020-02-26 10:45:00 CST / 1582735500 --> <row><v>NaN</v><v>NaN</v></row>
			<!-- 2020-02-26 10:46:00 CST / 1582735560 --> <row><v>NaN</v><v>NaN</v></row>
			<!-- 2020-02-26 10:47:00 CST / 1582735620 --> <row><v>NaN</v><v>NaN</v></row>
			<!-- 2020-02-26 10:48:00 CST / 1582735680 --> <row><v>NaN</v><v>NaN</v></row>
			<!-- 2020-02-26 10:49:00 CST / 1582735740 --> <row><v>NaN</v><v>NaN</v></row>
			<!-- 2020-02-26 10:50:00 CST / 1582735800 --> <row><v>NaN</v><v>NaN</v></row>
			<!-- 2020-02-26 10:51:00 CST / 1582735860 --> <row><v>NaN</v><v>NaN</v></row>
			<!-- 2020-02-26 10:52:00 CST / 1582735920 --> <row><v>NaN</v><v>NaN</v></row>
			<!-- 2020-02-26 10:53:00 CST / 1582735980 --> <row><v>NaN</v><v>NaN</v></row>
			<!-- 2020-02-26 10:54:00 CST / 1582736040 --> <row><v>NaN</v><v>NaN</v></row>
			<!-- 2020-02-26 10:55:00 CST / 1582736100 --> <row><v>NaN</v><v>NaN</v></row>
			<!-- 2020-02-26 10:56:00 CST / 1582736160 --> <row><v>NaN</v><v>NaN</v></row>
			<!-- 2020-02-26 10:57:00 CST / 1582736220 --> <row><v>NaN</v><v>NaN</v></row>
			<!-- 2020-02-26 10:58:00 CST / 1582736280 --> <row><v>NaN</v><v>NaN</v></row>
			<!-- 2020-02-26 10:59:00 CST / 1582736340 --> <row><v>NaN</v><v>NaN</v></row>
			<!-- 2020-02-26 11:00:00 CST / 1582736400 --> <row><v>NaN</v><v>NaN</v></row>
			<!-- 2020-02-26 11:01:00 CST / 1582736460 --> <row><v>NaN</v><v>NaN</v></row>
			<!-- 2020-02-26 11:02:00 CST / 1582736520 --> <row><v>NaN</v><v>NaN</v></row>
			<!-- 2020-02-26 11:03:00 CST / 1582736580 --> <row><v>NaN</v><v>NaN</v></row>
			<!-- 2020-02-26 11:04:00 CST / 1582736640 --> <row><v>NaN</v><v>NaN</v></row>
			<!-- 2020-02-26 11:05:00 CST / 1582736700 --> <row><v>NaN</v><v>NaN</v></row>
			<!-- 2020-02-26 11:06:00 CST / 1582736760 --> <row><v>NaN</v><v>NaN</v></row>
			<!-- 2020-02-26 11:07:00 CST / 1582736820 --> <row><v>NaN</v><v>NaN</v></row>
			<!-- 2020-02-26 11:08:00 CST / 1582736880 --> <row><v>NaN</v><v>NaN</v></row>
			<!-- 2020-02-26 11:09:00 CST / 1582736940 --> <row><v>NaN</v><v>NaN</v></row>
			<!-- 2020-02-26 11:10:00 CST / 1582737000 --> <row><v>NaN</v><v>NaN</v></row>
			<!-- 2020-02-26 11:11:00 CST / 1582737060 --> <row><v>NaN</v><v>NaN</v></row>
			<!-- 2020-02-26 11:12:00 CST / 1582737120 --> <row><v>NaN</v><v>NaN</v></row>
			<!-- 2020-02-26 11:13:00 CST / 1582737180 --> <row><v>NaN</v><v>NaN</v></row>
			<!-- 2020-02-26 11:14:00 CST / 1582737240 --> <row><v>NaN</v><v>NaN</v></row>
			<!-- 2020-02-26 11:15:00 CST / 1582737300 --> <row><v>NaN</v><v>NaN</v></row>
			<!-- 2020-02-26 11:16:00 CST / 1582737360 --> <row><v>NaN</v><v>NaN</v></row>
			<!-- 2020-02-26 11:17:00 CST / 1582737420 --> <row><v>NaN</v><v>NaN</v></row>
			<!-- 2020-02-26 11:18:00 CST / 1582737480 --> <row><v>NaN</v><v>NaN</v></row>
			<!-- 2020-02-26 11:19:00 CST / 1582737540 --> <row><v>NaN</v><v>NaN</v></row>
			<!-- 2020-02-26 11:20:00 CST / 1582737600 --> <row><v>NaN</v><v>NaN</v></row>
			<!-- 2020-02-26 11:21:00 CST / 1582737660 --> <row><v>NaN</v><v>NaN</v></row>
			<!-- 2020-02-26 11:22:00 CST / 1582737720 --> <row><v>NaN</v><v>NaN</v></row>
			<!-- 2020-02-26 11:23:00 CST / 1582737780 --> <row><v>NaN</v><v>NaN</v></row>
			<!-- 2020-02-26 11:24:00 CST / 1582737840 --> <row><v>NaN</v><v>NaN</v></row>
			<!-- 2020-02-26 11:25:00 CST / 1582737900 --> <row><v>NaN</v><v>NaN</v></row>
			<!-- 2020-02-26 11:26:00 CST / 1582737960 --> <row><v>NaN</v><v>NaN</v></row>
			<!-- 2020-02-26 11:27:00 CST / 1582738020 --> <row><v>NaN</v><v>NaN</v></row>
			<!-- 2020-02-26 11:28:00 CST / 1582738080 --> <row><v>NaN</v><v>NaN</v></row>
			<!-- 2020-02-26 11:29:00 CST / 1582738140 --> <row><v>NaN</v><v>NaN</v></row>
			<!-- 2020-02-26 11:30:00 CST / 1582738200 --> <row><v>NaN</v><v>NaN</v></row>
			<!-- 2020-02-26 11:31:00 CST / 1582738260 --> <row><v>NaN</v><v>NaN</v></row>
			<!-- 2020-02-26 11:32:00 CST / 1582738320 --> <row><v>NaN</v><v>NaN</v></row>
			<!-- 2020-02-26 11:33:00 CST / 1582738380 --> <row><v>NaN</v><v>NaN</v></row>
			<!-- 2020-02-26 11:34:00 CST / 1582738440 --> <row><v>NaN</v><v>NaN</v></row>
			<!-- 2020-02-26 11:35:00 CST / 1582738500 --> <row><v>NaN</v><v>NaN</v></row>
			<!-- 2020-02-26 11:36:00 CST / 1582738560 --> <row><v>NaN</v><v>NaN</v></row>
			<!-- 2020-02-26 11:37:00 CST / 1582738620 --> <row><v>NaN</v><v>NaN</v></row>
			<!-- 2020-02-26 11:38:00 CST / 1582738680 --> <row><v>NaN</v><v>NaN</v></row>
			<!-- 2020-02-26 11:39:00 CST / 1582738740 --> <row><v>NaN</v><v>NaN</v></row>
			<!-- 2020-02-26 11:40:00 CST / 1582738800 --> <row><v>NaN</v><v>NaN</v></row>
			<!-- 2020-02-26 11:41:00 CST / 1582738860 --> <row><v>NaN</v><v>NaN</v></row>
			<!-- 2020-02-26 11:42:00 CST / 1582738920 --> <row><v>NaN</v><v>NaN</v></row>
			<!-- 2020-02-26 11:43:00 CST / 1582738980 --> <row><v>NaN</v><v>NaN</v></row>
			<!-- 2020-02-26 11:44:00 CST / 1582739040 --> <row><v>NaN</v><v>NaN</v></row>
			<!-- 2020-02-26 11:45:00 CST / 1582739100 --> <row><v>NaN</v><v>NaN</v></row>
			<!-- 2020-02-26 11:46:00 CST / 1582739160 --> <row><v>NaN</v><v>NaN</v></row>
			<!-- 2020-02-26 11:47:00 CST / 1582739220 --> <row><v>NaN</v><v>NaN</v></row>
			<!-- 2020-02-26 11:48:00 CST / 1582739280 --> <row><v>NaN</v><v>NaN</v></row>
			<!-- 2020-02-26 11:49:00 CST / 1582739340 --> <row><v>NaN</v><v>NaN</v></row>
			<!-- 2020-02-26 11:50:00 CST / 1582739400 --> <row><v>NaN</v><v>NaN</v></row>
			<!-- 2020-02-26 11:51:00 CST / 1582739460 --> <row><v>NaN</v><v>NaN</v></row>
			<!-- 2020-02-26 11:52:00 CST / 1582739520 --> <row><v>NaN</v><v>NaN</v></row>
			<!-- 2020-02-26 11:53:00 CST / 1582739580 --> <row><v>NaN</v><v>NaN</v></row>
			<!-- 2020-02-26 11:54:00 CST / 1582739640 --> <row><v>NaN</v><v>NaN</v></row>
			<!-- 2020-02-26 11:55:00 CST / 1582739700 --> <row><v>NaN</v><v>NaN</v></row>
			<!-- 2020-02-26 11:56:00 CST / 1582739760 --> <row><v>NaN</v><v>NaN</v></row>
			<!-- 2020-02-26 11:57:00 CST / 1582739820 --> <row><v>NaN</v><v>NaN</v></row>
			<!-- 2020-02-26 11:58:00 CST / 1582739880 --> <row><v>NaN</v><v>NaN</v></row>
			<!-- 2020-02-26 11:59:00 CST / 1582739940 --> <row><v>NaN</v><v>NaN</v></row>
			<!-- 2020-02-26 12:00:00 CST / 1582740000 --> <row><v>NaN</v><v>NaN</v></row>
			<!-- 2020-02-26 12:01:00 CST / 1582740060 --> <row><v>NaN</v><v>NaN</v></row>
			<!-- 2020-02-26 12:02:00 CST / 1582740120 --> <row><v>NaN</v><v>NaN</v></row>
			<!-- 2020-02-26 12:03:00 CST / 1582740180 --> <row><v>NaN</v><v>NaN</v></row>
			<!-- 2020-02-26 12:04:00 CST / 1582740240 --> <row><v>NaN</v><v>NaN</v></row>
			<!-- 2020-02-26 12:05:00 CST / 1582740300 --> <row><v>NaN</v><v>NaN</v></row>
			<!-- 2020-02-26 12:06:00 CST / 1582740360 --> <row><v>NaN</v><v>NaN</v></row>
			<!-- 2020-02-26 12:07:00 CST / 1582740420 --> <row><v>NaN</v><v>NaN</v></row>
			<!-- 2020-02-26 12:08:00 CST / 1582740480 --> <row><v>NaN</v><v>NaN</v></row>
			<!-- 2020-02-26 12:09:00 CST / 1582740540 --> <row><v>NaN</v><v>NaN</v></row>
			<!-- 2020-02-26 12:10:00 CST / 1582740600 --> <row><v>NaN</v><v>NaN</v></row>
			<!-- 2020-02-26 12:11:00 CST / 1582740660 --> <row><v>NaN</v><v>NaN</v></row>
			<!-- 2020-02-26 12:12:00 CST / 1582740720 --> <row><v>NaN</v><v>NaN</v></row>
			<!-- 2020-02-26 12:13:00 CST / 1582740780 --> <row><v>NaN</v><v>NaN</v></row>
			<!-- 2020-02-26 12:14:00 CST / 1582740840 --> <row><v>NaN</v><v>NaN</v></row>
			<!-- 2020-02-26 12:15:00 CST / 1582740900 --> <row><v>NaN</v><v>NaN</v></row>
			<!-- 2020-02-26 12:16:00 CST / 1582740960 --> <row><v>NaN</v><v>NaN</v></row>
			<!-- 2020-02-26 12:17:00 CST / 1582741020 --> <row><v>NaN</v><v>NaN</v></row>
			<!-- 2020-02-26 12:18:00 CST / 1582741080 --> <row><v>NaN</v><v>NaN</v></row>
			<!-- 2020-02-26 12:19:00 CST / 1582741140 --> <row><v>NaN</v><v>NaN</v></row>
			<!-- 2020-02-26 12:20:00 CST / 1582741200 --> <row><v>NaN</v><v>NaN</v></row>
			<!-- 2020-02-26 12:21:00 CST / 1582741260 --> <row><v>NaN</v><v>NaN</v></row>
			<!-- 2020-02-26 12:22:00 CST / 1582741320 --> <row><v>NaN</v><v>NaN</v></row>
			<!-- 2020-02-26 12:23:00 CST / 1582741380 --> <row><v>NaN</v><v>NaN</v></row>
			<!-- 2020-02-26 12:24:00 CST / 1582741440 --> <row><v>NaN</v><v>NaN</v></row>
			<!-- 2020-02-26 12:25:00 CST / 1582741500 --> <row><v>NaN</v><v>NaN</v></row>
			<!-- 2020-02-26 12:26:00 CST / 1582741560 --> <row><v>NaN</v><v>NaN</v></row>
			<!-- 2020-02-26 12:27:00 CST / 1582741620 --> <row><v>NaN</v><v>NaN</v></row>
			<!-- 2020-02-26 12:28:00 CST / 1582741680 --> <row><v>NaN</v><v>NaN</v></row>
			<!-- 2020-02-26 12:29:00 CST / 1582741740 --> <row><v>NaN</v><v>NaN</v></row>
			<!-- 2020-02-26 12:30:00 CST / 1582741800 --> <row><v>NaN</v><v>NaN</v></row>
			<!-- 2020-02-26 12:31:00 CST / 1582741860 --> <row><v>NaN</v><v>NaN</v></row>
			<!-- 2020-02-26 12:32:00 CST / 1582741920 --> <row><v>NaN</v><v>NaN</v></row>
			<!-- 2020-02-26 12:33:00 CST / 1582741980 --> <row><v>NaN</v><v>NaN</v></row>
			<!-- 2020-02-26 12:34:00 CST / 1582742040 --> <row><v>NaN</v><v>NaN</v></row>
			<!-- 2020-02-26 12:35:00 CST / 1582742100 --> <row><v>NaN</v><v>NaN</v></row>
			<!-- 2020-02-26 12:36:00 CST / 1582742160 --> <row><v>NaN</v><v>NaN</v></row>
			<!-- 2020-02-26 12:37:00 CST / 1582742220 --> <row><v>NaN</v><v>NaN</v></row>
			<!-- 2020-02-26 12:38:00 CST / 1582742280 --> <row><v>NaN</v><v>NaN</v></row>
			<!-- 2020-02-26 12:39:00 CST / 1582742340 --> <row><v>NaN</v><v>NaN</v></row>
			<!-- 2020-02-26 12:40:00 CST / 1582742400 --> <row><v>NaN</v><v>NaN</v></row>
			<!-- 2020-02-26 12:41:00 CST / 1582742460 --> <row><v>NaN</v><v>NaN</v></row>
			<!-- 2020-02-26 12:42:00 CST / 1582742520 --> <row><v>NaN</v><v>NaN</v></row>
			<!-- 2020-02-26 12:43:00 CST / 1582742580 --> <row><v>NaN</v><v>NaN</v></row>
			<!-- 2020-02-26 12:44:00 CST / 1582742640 --> <row><v>NaN</v><v>NaN</v></row>
			<!-- 2020-02-26 12:45:00 CST / 1582742700 --> <row><v>NaN</v><v>NaN</v></row>
			<!-- 2020-02-26 12:46:00 CST / 1582742760 --> <row><v>NaN</v><v>NaN</v></row>
			<!-- 2020-02-26 12:47:00 CST / 1582742820 --> <row><v>NaN</v><v>NaN</v></row>
			<!-- 2020-02-26 12:48:00 CST / 1582742880 --> <row><v>NaN</v><v>NaN</v></row>
			<!-- 2020-02-26 12:49:00 CST / 1582742940 --> <row><v>NaN</v><v>NaN</v></row>
			<!-- 2020-02-26 12:50:00 CST / 1582743000 --> <row><v>NaN</v><v>NaN</v></row>
			<!-- 2020-02-26 12:51:00 CST / 1582743060 --> <row><v>NaN</v><v>NaN</v></row>
			<!-- 2020-02-26 12:52:00 CST / 1582743120 --> <row><v>NaN</v><v>NaN</v></row>
			<!-- 2020-02-26 12:53:00 CST / 1582743180 --> <row><v>NaN</v><v>NaN</v></row>
			<!-- 2020-02-26 12:54:00 CST / 1582743240 --> <row><v>NaN</v><v>NaN</v></row>
			<!-- 2020-02-26 12:55:00 CST / 1582743300 --> <row><v>NaN</v><v>NaN</v></row>
			<!-- 2020-02-26 12:56:00 CST / 1582743360 --> <row><v>NaN</v><v>NaN</v></row>
			<!-- 2020-02-26 12:57:00 CST / 1582743420 --> <row><v>NaN</v><v>NaN</v></row>
			<!-- 2020-02-26 12:58:00 CST / 1582743480 --> <row><v>NaN</v><v>NaN</v></row>
			<!-- 2020-02-26 12:59:00 CST / 1582743540 --> <row><v>NaN</v><v>NaN</v></row>
			<!-- 2020-02-26 13:00:00 CST / 1582743600 --> <row><v>NaN</v><v>NaN</v></row>
			<!-- 2020-02-26 13:01:00 CST / 1582743660 --> <row><v>NaN</v><v>NaN</v></row>
			<!-- 2020-02-26 13:02:00 CST / 1582743720 --> <row><v>NaN</v><v>NaN</v></row>
			<!-- 2020-02-26 13:03:00 CST / 1582743780 --> <row><v>NaN</v><v>NaN</v></row>
			<!-- 2020-02-26 13:04:00 CST / 1582743840 --> <row><v>NaN</v><v>NaN</v></row>
			<!-- 2020-02-26 13:05:00 CST / 1582743900 --> <row><v>NaN</v><v>NaN</v></row>
			<!-- 2020-02-26 13:06:00 CST / 1582743960 --> <row><v>NaN</v><v>NaN</v></row>
			<!-- 2020-02-26 13:07:00 CST / 1582744020 --> <row><v>NaN</v><v>NaN</v></row>
			<!-- 2020-02-26 13:08:00 CST / 1582744080 --> <row><v>NaN</v><v>NaN</v></row>
			<!-- 2020-02-26 13:09:00 CST / 1582744140 --> <row><v>NaN</v><v>NaN</v></row>
			<!-- 2020-02-26 13:10:00 CST / 1582744200 --> <row><v>NaN</v><v>NaN</v></row>
			<!-- 2020-02-26 13:11:00 CST / 1582744260 --> <row><v>NaN</v><v>NaN</v></row>
			<!-- 2020-02-26 13:12:00 CST / 1582744320 --> <row><v>NaN</v><v>NaN</v></row>
			<!-- 2020-02-26 13:13:00 CST / 1582744380 --> <row><v>NaN</v><v>NaN</v></row>
			<!-- 2020-02-26 13:14:00 CST / 1582744440 --> <row><v>NaN</v><v>NaN</v></row>
			<!-- 2020-02-26 13:15:00 CST / 1582744500 --> <row><v>NaN</v><v>NaN</v></row>
			<!-- 2020-02-26 13:16:00 CST / 1582744560 --> <row><v>NaN</v><v>NaN</v></row>
			<!-- 2020-02-26 13:17:00 CST / 1582744620 --> <row><v>NaN</v><v>NaN</v></row>
			<!-- 2020-02-26 13:18:00 CST / 1582744680 --> <row><v>NaN</v><v>NaN</v></row>
			<!-- 2020-02-26 13:19:00 CST / 1582744740 --> <row><v>NaN</v><v>NaN</v></row>
			<!-- 2020-02-26 13:20:00 CST / 1582744800 --> <row><v>NaN</v><v>NaN</v></row>
			<!-- 2020-02-26 13:21:00 CST / 1582744860 --> <row><v>NaN</v><v>NaN</v></row>
			<!-- 2020-02-26 13:22:00 CST / 1582744920 --> <row><v>NaN</v><v>NaN</v></row>
			<!-- 2020-02-26 13:23:00 CST / 1582744980 --> <row><v>NaN</v><v>NaN</v></row>
			<!-- 2020-02-26 13:24:00 CST / 1582745040 --> <row><v>NaN</v><v>NaN</v></row>
			<!-- 2020-02-26 13:25:00 CST / 1582745100 --> <row><v>NaN</v><v>NaN</v></row>
			<!-- 2020-02-26 13:26:00 CST / 1582745160 --> <row><v>NaN</v><v>NaN</v></row>
			<!-- 2020-02-26 13:27:00 CST / 1582745220 --> <row><v>NaN</v><v>NaN</v></row>
			<!-- 2020-02-26 13:28:00 CST / 1582745280 --> <row><v>NaN</v><v>NaN</v></row>
			<!-- 2020-02-26 13:29:00 CST / 1582745340 --> <row><v>NaN</v><v>NaN</v></row>
			<!-- 2020-02-26 13:30:00 CST / 1582745400 --> <row><v>NaN</v><v>NaN</v></row>
			<!-- 2020-02-26 13:31:00 CST / 1582745460 --> <row><v>NaN</v><v>NaN</v></row>
			<!-- 2020-02-26 13:32:00 CST / 1582745520 --> <row><v>NaN</v><v>NaN</v></row>
			<!-- 2020-02-26 13:33:00 CST / 1582745580 --> <row><v>NaN</v><v>NaN</v></row>
			<!-- 2020-02-26 13:34:00 CST / 1582745640 --> <row><v>NaN</v><v>NaN</v></row>
			<!-- 2020-02-26 13:35:00 CST / 1582745700 --> <row><v>NaN</v><v>NaN</v></row>
			<!-- 2020-02-26 13:36:00 CST / 1582745760 --> <row><v>NaN</v><v>NaN</v></row>
			<!-- 2020-02-26 13:37:00 CST / 1582745820 --> <row><v>NaN</v><v>NaN</v></row>
			<!-- 2020-02-26 13:38:00 CST / 1582745880 --> <row><v>NaN</v><v>NaN</v></row>
			<!-- 2020-02-26 13:39:00 CST / 1582745940 --> <row><v>NaN</v><v>NaN</v></row>
			<!-- 2020-02-26 13:40:00 CST / 1582746000 --> <row><v>NaN</v><v>NaN</v></row>
			<!-- 2020-02-26 13:41:00 CST / 1582746060 --> <row><v>NaN</v><v>NaN</v></row>
			<!-- 2020-02-26 13:42:00 CST / 1582746120 --> <row><v>NaN</v><v>NaN</v></row>
			<!-- 2020-02-26 13:43:00 CST / 1582746180 --> <row><v>NaN</v><v>NaN</v></row>
			<!-- 2020-02-26 13:44:00 CST / 1582746240 --> <row><v>NaN</v><v>NaN</v></row>
			<!-- 2020-02-26 13:45:00 CST / 1582746300 --> <row><v>NaN</v><v>NaN</v></row>
			<!-- 2020-02-26 13:46:00 CST / 1582746360 --> <row><v>NaN</v><v>NaN</v></row>
			<!-- 2020-02-26 13:47:00 CST / 1582746420 --> <row><v>NaN</v><v>NaN</v></row>
			<!-- 2020-02-26 13:48:00 CST / 1582746480 --> <row><v>NaN</v><v>NaN</v></row>
			<!-- 2020-02-26 13:49:00 CST / 1582746540 --> <row><v>NaN</v><v>NaN</v></row>
			<!-- 2020-02-26 13:50:00 CST / 1582746600 --> <row><v>NaN</v><v>NaN</v></row>
			<!-- 2020-02-26 13:51:00 CST / 1582746660 --> <row><v>NaN</v><v>NaN</v></row>
			<!-- 2020-02-26 13:52:00 CST / 1582746720 --> <row><v>NaN</v><v>NaN</v></row>
			<!-- 2020-02-26 13:53:00 CST / 1582746780 --> <row><v>NaN</v><v>NaN</v></row>
			<!-- 2020-02-26 13:54:00 CST / 1582746840 --> <row><v>NaN</v><v>NaN</v></row>
			<!-- 2020-02-26 13:55:00 CST / 1582746900 --> <row><v>NaN</v><v>NaN</v></row>
			<!-- 2020-02-26 13:56:00 CST / 1582746960 --> <row><v>NaN</v><v>NaN</v></row>
			<!-- 2020-02-26 13:57:00 CST / 1582747020 --> <row><v>NaN</v><v>NaN</v></row>
			<!-- 2020-02-26 13:58:00 CST / 1582747080 --> <row><v>NaN</v><v>NaN</v></row>
			<!-- 2020-02-26 13:59:00 CST / 1582747140 --> <row><v>NaN</v><v>NaN</v></row>
			<!-- 2020-02-26 14:00:00 CST / 1582747200 --> <row><v>NaN</v><v>NaN</v></row>
			<!-- 2020-02-26 14:01:00 CST / 1582747260 --> <row><v>NaN</v><v>NaN</v></row>
			<!-- 2020-02-26 14:02:00 CST / 1582747320 --> <row><v>NaN</v><v>NaN</v></row>
			<!-- 2020-02-26 14:03:00 CST / 1582747380 --> <row><v>NaN</v><v>NaN</v></row>
			<!-- 2020-02-26 14:04:00 CST / 1582747440 --> <row><v>NaN</v><v>NaN</v></row>
			<!-- 2020-02-26 14:05:00 CST / 1582747500 --> <row><v>NaN</v><v>NaN</v></row>
			<!-- 2020-02-26 14:06:00 CST / 1582747560 --> <row><v>NaN</v><v>NaN</v></row>
			<!-- 2020-02-26 14:07:00 CST / 1582747620 --> <row><v>NaN</v><v>NaN</v></row>
			<!-- 2020-02-26 14:08:00 CST / 1582747680 --> <row><v>NaN</v><v>NaN</v></row>
			<!-- 2020-02-26 14:09:00 CST / 1582747740 --> <row><v>NaN</v><v>NaN</v></row>
			<!-- 2020-02-26 14:10:00 CST / 1582747800 --> <row><v>NaN</v><v>NaN</v></row>
			<!-- 2020-02-26 14:11:00 CST / 1582747860 --> <row><v>NaN</v><v>NaN</v></row>
			<!-- 2020-02-26 14:12:00 CST / 1582747920 --> <row><v>NaN</v><v>NaN</v></row>
			<!-- 2020-02-26 14:13:00 CST / 1582747980 --> <row><v>NaN</v><v>NaN</v></row>
			<!-- 2020-02-26 14:14:00 CST / 1582748040 --> <row><v>NaN</v><v>NaN</v></row>
			<!-- 2020-02-26 14:15:00 CST / 1582748100 --> <row><v>NaN</v><v>NaN</v></row>
			<!-- 2020-02-26 14:16:00 CST / 1582748160 --> <row><v>NaN</v><v>NaN</v></row>
			<!-- 2020-02-26 14:17:00 CST / 1582748220 --> <row><v>NaN</v><v>NaN</v></row>
			<!-- 2020-02-26 14:18:00 CST / 1582748280 --> <row><v>NaN</v><v>NaN</v></row>
			<!-- 2020-02-26 14:19:00 CST / 1582748340 --> <row><v>NaN</v><v>NaN</v></row>
			<!-- 2020-02-26 14:20:00 CST / 1582748400 --> <row><v>NaN</v><v>NaN</v></row>
			<!-- 2020-02-26 14:21:00 CST / 1582748460 --> <row><v>NaN</v><v>NaN</v></row>
			<!-- 2020-02-26 14:22:00 CST / 1582748520 --> <row><v>NaN</v><v>NaN</v></row>
			<!-- 2020-02-26 14:23:00 CST / 1582748580 --> <row><v>NaN</v><v>NaN</v></row>
			<!-- 2020-02-26 14:24:00 CST / 1582748640 --> <row><v>NaN</v><v>NaN</v></row>
			<!-- 2020-02-26 14:25:00 CST / 1582748700 --> <row><v>NaN</v><v>NaN</v></row>
			<!-- 2020-02-26 14:26:00 CST / 1582748760 --> <row><v>NaN</v><v>NaN</v></row>
			<!-- 2020-02-26 14:27:00 CST / 1582748820 --> <row><v>NaN</v><v>NaN</v></row>
			<!-- 2020-02-26 14:28:00 CST / 1582748880 --> <row><v>NaN</v><v>NaN</v></row>
			<!-- 2020-02-26 14:29:00 CST / 1582748940 --> <row><v>NaN</v><v>NaN</v></row>
			<!-- 2020-02-26 14:30:00 CST / 1582749000 --> <row><v>NaN</v><v>NaN</v></row>
			<!-- 2020-02-26 14:31:00 CST / 1582749060 --> <row><v>NaN</v><v>NaN</v></row>
			<!-- 2020-02-26 14:32:00 CST / 1582749120 --> <row><v>NaN</v><v>NaN</v></row>
			<!-- 2020-02-26 14:33:00 CST / 1582749180 --> <row><v>NaN</v><v>NaN</v></row>
			<!-- 2020-02-26 14:34:00 CST / 1582749240 --> <row><v>NaN</v><v>NaN</v></row>
			<!-- 2020-02-26 14:35:00 CST / 1582749300 --> <row><v>NaN</v><v>NaN</v></row>
			<!-- 2020-02-26 14:36:00 CST / 1582749360 --> <row><v>NaN</v><v>NaN</v></row>
			<!-- 2020-02-26 14:37:00 CST / 1582749420 --> <row><v>NaN</v><v>NaN</v></row>
			<!-- 2020-02-26 14:38:00 CST / 1582749480 --> <row><v>NaN</v><v>NaN</v></row>
			<!-- 2020-02-26 14:39:00 CST / 1582749540 --> <row><v>NaN</v><v>NaN</v></row>
			<!-- 2020-02-26 14:40:00 CST / 1582749600 --> <row><v>NaN</v><v>NaN</v></row>
			<!-- 2020-02-26 14:41:00 CST / 1582749660 --> <row><v>NaN</v><v>NaN</v></row>
			<!-- 2020-02-26 14:42:00 CST / 1582749720 --> <row><v>NaN</v><v>NaN</v></row>
			<!-- 2020-02-26 14:43:00 CST / 1582749780 --> <row><v>NaN</v><v>NaN</v></row>
			<!-- 2020-02-26 14:44:00 CST / 1582749840 --> <row><v>NaN</v><v>NaN</v></row>
			<!-- 2020-02-26 14:45:00 CST / 1582749900 --> <row><v>NaN</v><v>NaN</v></row>
			<!-- 2020-02-26 14:46:00 CST / 1582749960 --> <row><v>NaN</v><v>NaN</v></row>
			<!-- 2020-02-26 14:47:00 CST / 1582750020 --> <row><v>NaN</v><v>NaN</v></row>
			<!-- 2020-02-26 14:48:00 CST / 1582750080 --> <row><v>NaN</v><v>NaN</v></row>
			<!-- 2020-02-26 14:49:00 CST / 1582750140 --> <row><v>NaN</v><v>NaN</v></row>
			<!-- 2020-02-26 14:50:00 CST / 1582750200 --> <row><v>NaN</v><v>NaN</v></row>
			<!-- 2020-02-26 14:51:00 CST / 1582750260 --> <row><v>NaN</v><v>NaN</v></row>
			<!-- 2020-02-26 14:52:00 CST / 1582750320 --> <row><v>NaN</v><v>NaN</v></row>
			<!-- 2020-02-26 14:53:00 CST / 1582750380 --> <row><v>NaN</v><v>NaN</v></row>
			<!-- 2020-02-26 14:54:00 CST / 1582750440 --> <row><v>NaN</v><v>NaN</v></row>
			<!-- 2020-02-26 14:55:00 CST / 1582750500 --> <row><v>NaN</v><v>NaN</v></row>
			<!-- 2020-02-26 14:56:00 CST / 1582750560 --> <row><v>NaN</v><v>NaN</v></row>
			<!-- 2020-02-26 14:57:00 CST / 1582750620 --> <row><v>NaN</v><v>NaN</v></row>
			<!-- 2020-02-26 14:58:00 CST / 1582750680 --> <row><v>NaN</v><v>NaN</v></row>
			<!-- 2020-02-26 14:59:00 CST / 1582750740 --> <row><v>NaN</v><v>NaN</v></row>
			<!-- 2020-02-26 15:00:00 CST / 1582750800 --> <row><v>NaN</v><v>NaN</v></row>
			<!-- 2020-02-26 15:01:00 CST / 1582750860 --> <row><v>NaN</v><v>NaN</v></row>
			<!-- 2020-02-26 15:02:00 CST / 1582750920 --> <row><v>NaN</v><v>NaN</v></row>
			<!-- 2020-02-26 15:03:00 CST / 1582750980 --> <row><v>NaN</v><v>NaN</v></row>
			<!-- 2020-02-26 15:04:00 CST / 1582751040 --> <row><v>NaN</v><v>NaN</v></row>
			<!-- 2020-02-26 15:05:00 CST / 1582751100 --> <row><v>NaN</v><v>NaN</v></row>
			<!-- 2020-02-26 15:06:00 CST / 1582751160 --> <row><v>NaN</v><v>NaN</v></row>
			<!-- 2020-02-26 15:07:00 CST / 1582751220 --> <row><v>NaN</v><v>NaN</v></row>
			<!-- 2020-02-26 15:08:00 CST / 1582751280 --> <row><v>NaN</v><v>NaN</v></row>
			<!-- 2020-02-26 15:09:00 CST / 1582751340 --> <row><v>NaN</v><v>NaN</v></row>
			<!-- 2020-02-26 15:10:00 CST / 1582751400 --> <row><v>NaN</v><v>NaN</v></row>
			<!-- 2020-02-26 15:11:00 CST / 1582751460 --> <row><v>NaN</v><v>NaN</v></row>
			<!-- 2020-02-26 15:12:00 CST / 1582751520 --> <row><v>NaN</v><v>NaN</v></row>
			<!-- 2020-02-26 15:13:00 CST / 1582751580 --> <row><v>NaN</v><v>NaN</v></row>
			<!-- 2020-02-26 15:14:00 CST / 1582751640 --> <row><v>NaN</v><v>NaN</v></row>
			<!-- 2020-02-26 15:15:00 CST / 1582751700 --> <row><v>NaN</v><v>NaN</v></row>
			<!-- 2020-02-26 15:16:00 CST / 1582751760 --> <row><v>NaN</v><v>NaN</v></row>
			<!-- 2020-02-26 15:17:00 CST / 1582751820 --> <row><v>NaN</v><v>NaN</v></row>
			<!-- 2020-02-26 15:18:00 CST / 1582751880 --> <row><v>NaN</v><v>NaN</v></row>
			<!-- 2020-02-26 15:19:00 CST / 1582751940 --> <row><v>NaN</v><v>NaN</v></row>
			<!-- 2020-02-26 15:20:00 CST / 1582752000 --> <row><v>NaN</v><v>NaN</v></row>
			<!-- 2020-02-26 15:21:00 CST / 1582752060 --> <row><v>NaN</v><v>NaN</v></row>
			<!-- 2020-02-26 15:22:00 CST / 1582752120 --> <row><v>NaN</v><v>NaN</v></row>
			<!-- 2020-02-26 15:23:00 CST / 1582752180 --> <row><v>NaN</v><v>NaN</v></row>
			<!-- 2020-02-26 15:24:00 CST / 1582752240 --> <row><v>NaN</v><v>NaN</v></row>
			<!-- 2020-02-26 15:25:00 CST / 1582752300 --> <row><v>NaN</v><v>NaN</v></row>
			<!-- 2020-02-26 15:26:00 CST / 1582752360 --> <row><v>NaN</v><v>NaN</v></row>
			<!-- 2020-02-26 15:27:00 CST / 1582752420 --> <row><v>NaN</v><v>NaN</v></row>
			<!-- 2020-02-26 15:28:00 CST / 1582752480 --> <row><v>NaN</v><v>NaN</v></row>
			<!-- 2020-02-26 15:29:00 CST / 1582752540 --> <row><v>NaN</v><v>NaN</v></row>
			<!-- 2020-02-26 15:30:00 CST / 1582752600 --> <row><v>NaN</v><v>NaN</v></row>
			<!-- 2020-02-26 15:31:00 CST / 1582752660 --> <row><v>NaN</v><v>NaN</v></row>
			<!-- 2020-02-26 15:32:00 CST / 1582752720 --> <row><v>NaN</v><v>NaN</v></row>
			<!-- 2020-02-26 15:33:00 CST / 1582752780 --> <row><v>NaN</v><v>NaN</v></row>
			<!-- 2020-02-26 15:34:00 CST / 1582752840 --> <row><v>NaN</v><v>NaN</v></row>
			<!-- 2020-02-26 15:35:00 CST / 1582752900 --> <row><v>NaN</v><v>NaN</v></row>
			<!-- 2020-02-26 15:36:00 CST / 1582752960 --> <row><v>NaN</v><v>NaN</v></row>
			<!-- 2020-02-26 15:37:00 CST / 1582753020 --> <row><v>NaN</v><v>NaN</v></row>
			<!-- 2020-02-26 15:38:00 CST / 1582753080 --> <row><v>NaN</v><v>NaN</v></row>
			<!-- 2020-02-26 15:39:00 CST / 1582753140 --> <row><v>NaN</v><v>NaN</v></row>
			<!-- 2020-02-26 15:40:00 CST / 1582753200 --> <row><v>NaN</v><v>NaN</v></row>
			<!-- 2020-02-26 15:41:00 CST / 1582753260 --> <row><v>NaN</v><v>NaN</v></row>
			<!-- 2020-02-26 15:42:00 CST / 1582753320 --> <row><v>NaN</v><v>NaN</v></row>
			<!-- 2020-02-26 15:43:00 CST / 1582753380 --> <row><v>NaN</v><v>NaN</v></row>
			<!-- 2020-02-26 15:44:00 CST / 1582753440 --> <row><v>NaN</v><v>NaN</v></row>
			<!-- 2020-02-26 15:45:00 CST / 1582753500 --> <row><v>NaN</v><v>NaN</v></row>
			<!-- 2020-02-26 15:46:00 CST / 1582753560 --> <row><v>NaN</v><v>NaN</v></row>
			<!-- 2020-02-26 15:47:00 CST / 1582753620 --> <row><v>NaN</v><v>NaN</v></row>
			<!-- 2020-02-26 15:48:00 CST / 1582753680 --> <row><v>NaN</v><v>NaN</v></row>
			<!-- 2020-02-26 15:49:00 CST / 1582753740 --> <row><v>NaN</v><v>NaN</v></row>
			<!-- 2020-02-26 15:50:00 CST / 1582753800 --> <row><v>NaN</v><v>NaN</v></row>
			<!-- 2020-02-26 15:51:00 CST / 1582753860 --> <row><v>NaN</v><v>NaN</v></row>
			<!-- 2020-02-26 15:52:00 CST / 1582753920 --> <row><v>NaN</v><v>NaN</v></row>
			<!-- 2020-02-26 15:53:00 CST / 1582753980 --> <row><v>NaN</v><v>NaN</v></row>
			<!-- 2020-02-26 15:54:00 CST / 1582754040 --> <row><v>NaN</v><v>NaN</v></row>
			<!-- 2020-02-26 15:55:00 CST / 1582754100 --> <row><v>NaN</v><v>NaN</v></row>
			<!-- 2020-02-26 15:56:00 CST / 1582754160 --> <row><v>NaN</v><v>NaN</v></row>
			<!-- 2020-02-26 15:57:00 CST / 1582754220 --> <row><v>NaN</v><v>NaN</v></row>
			<!-- 2020-02-26 15:58:00 CST / 1582754280 --> <row><v>NaN</v><v>NaN</v></row>
			<!-- 2020-02-26 15:59:00 CST / 1582754340 --> <row><v>NaN</v><v>NaN</v></row>
			<!-- 2020-02-26 16:00:00 CST / 1582754400 --> <row><v>NaN</v><v>NaN</v></row>
			<!-- 2020-02-26 16:01:00 CST / 1582754460 --> <row><v>NaN</v><v>NaN</v></row>
			<!-- 2020-02-26 16:02:00 CST / 1582754520 --> <row><v>NaN</v><v>NaN</v></row>
			<!-- 2020-02-26 16:03:00 CST / 1582754580 --> <row><v>NaN</v><v>NaN</v></row>
			<!-- 2020-02-26 16:04:00 CST / 1582754640 --> <row><v>NaN</v><v>NaN</v></row>
			<!-- 2020-02-26 16:05:00 CST / 1582754700 --> <row><v>NaN</v><v>NaN</v></row>
			<!-- 2020-02-26 16:06:00 CST / 1582754760 --> <row><v>NaN</v><v>NaN</v></row>
			<!-- 2020-02-26 16:07:00 CST / 1582754820 --> <row><v>NaN</v><v>NaN</v></row>
			<!-- 2020-02-26 16:08:00 CST / 1582754880 --> <row><v>NaN</v><v>NaN</v></row>
			<!-- 2020-02-26 16:09:00 CST / 1582754940 --> <row><v>NaN</v><v>NaN</v></row>
			<!-- 2020-02-26 16:10:00 CST / 1582755000 --> <row><v>NaN</v><v>NaN</v></row>
			<!-- 2020-02-26 16:11:00 CST / 1582755060 --> <row><v>NaN</v><v>NaN</v></row>
			<!-- 2020-02-26 16:12:00 CST / 1582755120 --> <row><v>NaN</v><v>NaN</v></row>
			<!-- 2020-02-26 16:13:00 CST / 1582755180 --> <row><v>NaN</v><v>NaN</v></row>
			<!-- 2020-02-26 16:14:00 CST / 1582755240 --> <row><v>NaN</v><v>NaN</v></row>
			<!-- 2020-02-26 16:15:00 CST / 1582755300 --> <row><v>NaN</v><v>NaN</v></row>
			<!-- 2020-02-26 16:16:00 CST / 1582755360 --> <row><v>NaN</v><v>NaN</v></row>
			<!-- 2020-02-26 16:17:00 CST / 1582755420 --> <row><v>NaN</v><v>NaN</v></row>
			<!-- 2020-02-26 16:18:00 CST / 1582755480 --> <row><v>NaN</v><v>NaN</v></row>
			<!-- 2020-02-26 16:19:00 CST / 1582755540 --> <row><v>NaN</v><v>NaN</v></row>
			<!-- 2020-02-26 16:20:00 CST / 1582755600 --> <row><v>NaN</v><v>NaN</v></row>
			<!-- 2020-02-26 16:21:00 CST / 1582755660 --> <row><v>NaN</v><v>NaN</v></row>
			<!-- 2020-02-26 16:22:00 CST / 1582755720 --> <row><v>NaN</v><v>NaN</v></row>
			<!-- 2020-02-26 16:23:00 CST / 1582755780 --> <row><v>NaN</v><v>NaN</v></row>
			<!-- 2020-02-26 16:24:00 CST / 1582755840 --> <row><v>NaN</v><v>NaN</v></row>
			<!-- 2020-02-26 16:25:00 CST / 1582755900 --> <row><v>NaN</v><v>NaN</v></row>
			<!-- 2020-02-26 16:26:00 CST / 1582755960 --> <row><v>NaN</v><v>NaN</v></row>
			<!-- 2020-02-26 16:27:00 CST / 1582756020 --> <row><v>NaN</v><v>NaN</v></row>
			<!-- 2020-02-26 16:28:00 CST / 1582756080 --> <row><v>NaN</v><v>NaN</v></row>
			<!-- 2020-02-26 16:29:00 CST / 1582756140 --> <row><v>NaN</v><v>NaN</v></row>
			<!-- 2020-02-26 16:30:00 CST / 1582756200 --> <row><v>NaN</v><v>NaN</v></row>
			<!-- 2020-02-26 16:31:00 CST / 1582756260 --> <row><v>NaN</v><v>NaN</v></row>
			<!-- 2020-02-26 16:32:00 CST / 1582756320 --> <row><v>NaN</v><v>NaN</v></row>
			<!-- 2020-02-26 16:33:00 CST / 1582756380 --> <row><v>NaN</v><v>NaN</v></row>
			<!-- 2020-02-26 16:34:00 CST / 1582756440 --> <row><v>NaN</v><v>NaN</v></row>
			<!-- 2020-02-26 16:35:00 CST / 1582756500 --> <row><v>NaN</v><v>NaN</v></row>
			<!-- 2020-02-26 16:36:00 CST / 1582756560 --> <row><v>NaN</v><v>NaN</v></row>
			<!-- 2020-02-26 16:37:00 CST / 1582756620 --> <row><v>NaN</v><v>NaN</v></row>
			<!-- 2020-02-26 16:38:00 CST / 1582756680 --> <row><v>NaN</v><v>NaN</v></row>
			<!-- 2020-02-26 16:39:00 CST / 1582756740 --> <row><v>NaN</v><v>NaN</v></row>
			<!-- 2020-02-26 16:40:00 CST / 1582756800 --> <row><v>NaN</v><v>NaN</v></row>
			<!-- 2020-02-26 16:41:00 CST / 1582756860 --> <row><v>NaN</v><v>NaN</v></row>
			<!-- 2020-02-26 16:42:00 CST / 1582756920 --> <row><v>NaN</v><v>NaN</v></row>
			<!-- 2020-02-26 16:43:00 CST / 1582756980 --> <row><v>NaN</v><v>NaN</v></row>
			<!-- 2020-02-26 16:44:00 CST / 1582757040 --> <row><v>NaN</v><v>NaN</v></row>
			<!-- 2020-02-26 16:45:00 CST / 1582757100 --> <row><v>NaN</v><v>NaN</v></row>
			<!-- 2020-02-26 16:46:00 CST / 1582757160 --> <row><v>NaN</v><v>NaN</v></row>
			<!-- 2020-02-26 16:47:00 CST / 1582757220 --> <row><v>NaN</v><v>NaN</v></row>
			<!-- 2020-02-26 16:48:00 CST / 1582757280 --> <row><v>NaN</v><v>NaN</v></row>
			<!-- 2020-02-26 16:49:00 CST / 1582757340 --> <row><v>NaN</v><v>NaN</v></row>
			<!-- 2020-02-26 16:50:00 CST / 1582757400 --> <row><v>NaN</v><v>NaN</v></row>
			<!-- 2020-02-26 16:51:00 CST / 1582757460 --> <row><v>NaN</v><v>NaN</v></row>
			<!-- 2020-02-26 16:52:00 CST / 1582757520 --> <row><v>NaN</v><v>NaN</v></row>
			<!-- 2020-02-26 16:53:00 CST / 1582757580 --> <row><v>NaN</v><v>NaN</v></row>
			<!-- 2020-02-26 16:54:00 CST / 1582757640 --> <row><v>NaN</v><v>NaN</v></row>
			<!-- 2020-02-26 16:55:00 CST / 1582757700 --> <row><v>NaN</v><v>NaN</v></row>
			<!-- 2020-02-26 16:56:00 CST / 1582757760 --> <row><v>NaN</v><v>NaN</v></row>
			<!-- 2020-02-26 16:57:00 CST / 1582757820 --> <row><v>NaN</v><v>NaN</v></row>
			<!-- 2020-02-26 16:58:00 CST / 1582757880 --> <row><v>NaN</v><v>NaN</v></row>
			<!-- 2020-02-26 16:59:00 CST / 1582757940 --> <row><v>NaN</v><v>NaN</v></row>
			<!-- 2020-02-26 17:00:00 CST / 1582758000 --> <row><v>NaN</v><v>NaN</v></row>
			<!-- 2020-02-26 17:01:00 CST / 1582758060 --> <row><v>NaN</v><v>NaN</v></row>
			<!-- 2020-02-26 17:02:00 CST / 1582758120 --> <row><v>NaN</v><v>NaN</v></row>
			<!-- 2020-02-26 17:03:00 CST / 1582758180 --> <row><v>NaN</v><v>NaN</v></row>
			<!-- 2020-02-26 17:04:00 CST / 1582758240 --> <row><v>NaN</v><v>NaN</v></row>
			<!-- 2020-02-26 17:05:00 CST / 1582758300 --> <row><v>NaN</v><v>NaN</v></row>
			<!-- 2020-02-26 17:06:00 CST / 1582758360 --> <row><v>NaN</v><v>NaN</v></row>
			<!-- 2020-02-26 17:07:00 CST / 1582758420 --> <row><v>NaN</v><v>NaN</v></row>
			<!-- 2020-02-26 17:08:00 CST / 1582758480 --> <row><v>NaN</v><v>NaN</v></row>
			<!-- 2020-02-26 17:09:00 CST / 1582758540 --> <row><v>NaN</v><v>NaN</v></row>
			<!-- 2020-02-26 17:10:00 CST / 1582758600 --> <row><v>NaN</v><v>NaN</v></row>
			<!-- 2020-02-26 17:11:00 CST / 1582758660 --> <row><v>NaN</v><v>NaN</v></row>
			<!-- 2020-02-26 17:12:00 CST / 1582758720 --> <row><v>NaN</v><v>NaN</v></row>
			<!-- 2020-02-26 17:13:00 CST / 1582758780 --> <row><v>NaN</v><v>NaN</v></row>
			<!-- 2020-02-26 17:14:00 CST / 1582758840 --> <row><v>NaN</v><v>NaN</v></row>
			<!-- 2020-02-26 17:15:00 CST / 1582758900 --> <row><v>NaN</v><v>NaN</v></row>
			<!-- 2020-02-26 17:16:00 CST / 1582758960 --> <row><v>NaN</v><v>NaN</v></row>
			<!-- 2020-02-26 17:17:00 CST / 1582759020 --> <row><v>NaN</v><v>NaN</v></row>
			<!-- 2020-02-26 17:18:00 CST / 1582759080 --> <row><v>NaN</v><v>NaN</v></row>
			<!-- 2020-02-26 17:19:00 CST / 1582759140 --> <row><v>NaN</v><v>NaN</v></row>
			<!-- 2020-02-26 17:20:00 CST / 1582759200 --> <row><v>NaN</v><v>NaN</v></row>
			<!-- 2020-02-26 17:21:00 CST / 1582759260 --> <row><v>NaN</v><v>NaN</v></row>
			<!-- 2020-02-26 17:22:00 CST / 1582759320 --> <row><v>NaN</v><v>NaN</v></row>
			<!-- 2020-02-26 17:23:00 CST / 1582759380 --> <row><v>NaN</v><v>NaN</v></row>
			<!-- 2020-02-26 17:24:00 CST / 1582759440 --> <row><v>NaN</v><v>NaN</v></row>
			<!-- 2020-02-26 17:25:00 CST / 1582759500 --> <row><v>NaN</v><v>NaN</v></row>
			<!-- 2020-02-26 17:26:00 CST / 1582759560 --> <row><v>NaN</v><v>NaN</v></row>
			<!-- 2020-02-26 17:27:00 CST / 1582759620 --> <row><v>NaN</v><v>NaN</v></row>
			<!-- 2020-02-26 17:28:00 CST / 1582759680 --> <row><v>NaN</v><v>NaN</v></row>
			<!-- 2020-02-26 17:29:00 CST / 1582759740 --> <row><v>NaN</v><v>NaN</v></row>
			<!-- 2020-02-26 17:30:00 CST / 1582759800 --> <row><v>NaN</v><v>NaN</v></row>
			<!-- 2020-02-26 17:31:00 CST / 1582759860 --> <row><v>NaN</v><v>NaN</v></row>
			<!-- 2020-02-26 17:32:00 CST / 1582759920 --> <row><v>NaN</v><v>NaN</v></row>
			<!-- 2020-02-26 17:33:00 CST / 1582759980 --> <row><v>NaN</v><v>NaN</v></row>
			<!-- 2020-02-26 17:34:00 CST / 1582760040 --> <row><v>NaN</v><v>NaN</v></row>
			<!-- 2020-02-26 17:35:00 CST / 1582760100 --> <row><v>NaN</v><v>NaN</v></row>
			<!-- 2020-02-26 17:36:00 CST / 1582760160 --> <row><v>NaN</v><v>NaN</v></row>
			<!-- 2020-02-26 17:37:00 CST / 1582760220 --> <row><v>NaN</v><v>NaN</v></row>
			<!-- 2020-02-26 17:38:00 CST / 1582760280 --> <row><v>NaN</v><v>NaN</v></row>
			<!-- 2020-02-26 17:39:00 CST / 1582760340 --> <row><v>NaN</v><v>NaN</v></row>
			<!-- 2020-02-26 17:40:00 CST / 1582760400 --> <row><v>NaN</v><v>NaN</v></row>
			<!-- 2020-02-26 17:41:00 CST / 1582760460 --> <row><v>NaN</v><v>NaN</v></row>
			<!-- 2020-02-26 17:42:00 CST / 1582760520 --> <row><v>NaN</v><v>NaN</v></row>
			<!-- 2020-02-26 17:43:00 CST / 1582760580 --> <row><v>NaN</v><v>NaN</v></row>
			<!-- 2020-02-26 17:44:00 CST / 1582760640 --> <row><v>NaN</v><v>NaN</v></row>
			<!-- 2020-02-26 17:45:00 CST / 1582760700 --> <row><v>NaN</v><v>NaN</v></row>
			<!-- 2020-02-26 17:46:00 CST / 1582760760 --> <row><v>NaN</v><v>NaN</v></row>
			<!-- 2020-02-26 17:47:00 CST / 1582760820 --> <row><v>NaN</v><v>NaN</v></row>
			<!-- 2020-02-26 17:48:00 CST / 1582760880 --> <row><v>NaN</v><v>NaN</v></row>
			<!-- 2020-02-26 17:49:00 CST / 1582760940 --> <row><v>NaN</v><v>NaN</v></row>
			<!-- 2020-02-26 17:50:00 CST / 1582761000 --> <row><v>NaN</v><v>NaN</v></row>
			<!-- 2020-02-26 17:51:00 CST / 1582761060 --> <row><v>NaN</v><v>NaN</v></row>
			<!-- 2020-02-26 17:52:00 CST / 1582761120 --> <row><v>NaN</v><v>NaN</v></row>
			<!-- 2020-02-26 17:53:00 CST / 1582761180 --> <row><v>NaN</v><v>NaN</v></row>
			<!-- 2020-02-26 17:54:00 CST / 1582761240 --> <row><v>NaN</v><v>NaN</v></row>
			<!-- 2020-02-26 17:55:00 CST / 1582761300 --> <row><v>NaN</v><v>NaN</v></row>
			<!-- 2020-02-26 17:56:00 CST / 1582761360 --> <row><v>NaN</v><v>NaN</v></row>
			<!-- 2020-02-26 17:57:00 CST / 1582761420 --> <row><v>NaN</v><v>NaN</v></row>
			<!-- 2020-02-26 17:58:00 CST / 1582761480 --> <row><v>NaN</v><v>NaN</v></row>
			<!-- 2020-02-26 17:59:00 CST / 1582761540 --> <row><v>NaN</v><v>NaN</v></row>
			<!-- 2020-02-26 18:00:00 CST / 1582761600 --> <row><v>NaN</v><v>NaN</v></row>
			<!-- 2020-02-26 18:01:00 CST / 1582761660 --> <row><v>NaN</v><v>NaN</v></row>
			<!-- 2020-02-26 18:02:00 CST / 1582761720 --> <row><v>NaN</v><v>NaN</v></row>
			<!-- 2020-02-26 18:03:00 CST / 1582761780 --> <row><v>NaN</v><v>NaN</v></row>
			<!-- 2020-02-26 18:04:00 CST / 1582761840 --> <row><v>NaN</v><v>NaN</v></row>
			<!-- 2020-02-26 18:05:00 CST / 1582761900 --> <row><v>NaN</v><v>NaN</v></row>
			<!-- 2020-02-26 18:06:00 CST / 1582761960 --> <row><v>NaN</v><v>NaN</v></row>
			<!-- 2020-02-26 18:07:00 CST / 1582762020 --> <row><v>NaN</v><v>NaN</v></row>
			<!-- 2020-02-26 18:08:00 CST / 1582762080 --> <row><v>NaN</v><v>NaN</v></row>
			<!-- 2020-02-26 18:09:00 CST / 1582762140 --> <row><v>NaN</v><v>NaN</v></row>
			<!-- 2020-02-26 18:10:00 CST / 1582762200 --> <row><v>NaN</v><v>NaN</v></row>
			<!-- 2020-02-26 18:11:00 CST / 1582762260 --> <row><v>NaN</v><v>NaN</v></row>
			<!-- 2020-02-26 18:12:00 CST / 1582762320 --> <row><v>NaN</v><v>NaN</v></row>
			<!-- 2020-02-26 18:13:00 CST / 1582762380 --> <row><v>NaN</v><v>NaN</v></row>
			<!-- 2020-02-26 18:14:00 CST / 1582762440 --> <row><v>NaN</v><v>NaN</v></row>
			<!-- 2020-02-26 18:15:00 CST / 1582762500 --> <row><v>NaN</v><v>NaN</v></row>
			<!-- 2020-02-26 18:16:00 CST / 1582762560 --> <row><v>NaN</v><v>NaN</v></row>
			<!-- 2020-02-26 18:17:00 CST / 1582762620 --> <row><v>NaN</v><v>NaN</v></row>
			<!-- 2020-02-26 18:18:00 CST / 1582762680 --> <row><v>NaN</v><v>NaN</v></row>
			<!-- 2020-02-26 18:19:00 CST / 1582762740 --> <row><v>NaN</v><v>NaN</v></row>
			<!-- 2020-02-26 18:20:00 CST / 1582762800 --> <row><v>NaN</v><v>NaN</v></row>
			<!-- 2020-02-26 18:21:00 CST / 1582762860 --> <row><v>NaN</v><v>NaN</v></row>
			<!-- 2020-02-26 18:22:00 CST / 1582762920 --> <row><v>NaN</v><v>NaN</v></row>
			<!-- 2020-02-26 18:23:00 CST / 1582762980 --> <row><v>NaN</v><v>NaN</v></row>
			<!-- 2020-02-26 18:24:00 CST / 1582763040 --> <row><v>NaN</v><v>NaN</v></row>
			<!-- 2020-02-26 18:25:00 CST / 1582763100 --> <row><v>NaN</v><v>NaN</v></row>
			<!-- 2020-02-26 18:26:00 CST / 1582763160 --> <row><v>NaN</v><v>NaN</v></row>
			<!-- 2020-02-26 18:27:00 CST / 1582763220 --> <row><v>NaN</v><v>NaN</v></row>
			<!-- 2020-02-26 18:28:00 CST / 1582763280 --> <row><v>NaN</v><v>NaN</v></row>
			<!-- 2020-02-26 18:29:00 CST / 1582763340 --> <row><v>NaN</v><v>NaN</v></row>
			<!-- 2020-02-26 18:30:00 CST / 1582763400 --> <row><v>NaN</v><v>NaN</v></row>
			<!-- 2020-02-26 18:31:00 CST / 1582763460 --> <row><v>NaN</v><v>NaN</v></row>
			<!-- 2020-02-26 18:32:00 CST / 1582763520 --> <row><v>NaN</v><v>NaN</v></row>
			<!-- 2020-02-26 18:33:00 CST / 1582763580 --> <row><v>NaN</v><v>NaN</v></row>
			<!-- 2020-02-26 18:34:00 CST / 1582763640 --> <row><v>NaN</v><v>NaN</v></row>
			<!-- 2020-02-26 18:35:00 CST / 1582763700 --> <row><v>NaN</v><v>NaN</v></row>
			<!-- 2020-02-26 18:36:00 CST / 1582763760 --> <row><v>NaN</v><v>NaN</v></row>
			<!-- 2020-02-26 18:37:00 CST / 1582763820 --> <row><v>NaN</v><v>NaN</v></row>
			<!-- 2020-02-26 18:38:00 CST / 1582763880 --> <row><v>NaN</v><v>NaN</v></row>
			<!-- 2020-02-26 18:39:00 CST / 1582763940 --> <row><v>NaN</v><v>NaN</v></row>
		</database>
	</rra>
</rrd>
